circpandas/__init__.py
circpandas/circseries.py
circpandas/version.py
circ_pandas-0.1.0.dist-info/LICENSE
circ_pandas-0.1.0.dist-info/METADATA
circ_pandas-0.1.0.dist-info/WHEEL
circ_pandas-0.1.0.dist-info/top_level.txt
circ_pandas-0.1.0.dist-info/RECORD
