Metadata-Version: 2.1
Name: circ-pandas
Version: 0.1.0
Summary: extending pandas data for circular data
Home-page: https://github.com/konnyakmannan/circ-pandas
Author: Taiki Kanda
Author-email: taiki@konnyak.com
License: MIT
Keywords: circular data,directional statistics,extending pandas
Platform: UNKNOWN
Classifier: Development Status :: 5 - Production/Stable
Classifier: Intended Audience :: Science/Research
Classifier: License :: OSI Approved :: MIT License
Classifier: Operating System :: OS Independent
Classifier: Programming Language :: Python
Classifier: Programming Language :: Python :: 3
Classifier: Programming Language :: Python :: 3 :: Only
Classifier: Programming Language :: Python :: 3.8
Classifier: Programming Language :: Python :: 3.9
Classifier: Programming Language :: Python :: 3.10
Classifier: Programming Language :: Python :: Implementation :: CPython
Classifier: Topic :: Scientific/Engineering
Requires-Python: >=3.8
License-File: LICENSE
Requires-Dist: pandas
Provides-Extra: test
Requires-Dist: mypy ; extra == 'test'
Requires-Dist: pandas-stubs ; extra == 'test'
Requires-Dist: pytest ; extra == 'test'
Requires-Dist: tox ; extra == 'test'
